opsml/__init__.py
opsml/__init__.pyi
opsml/app/__init__.py
opsml/app/__init__.pyi
opsml/card/__init__.py
opsml/card/__init__.pyi
opsml/cli/__init__.py
opsml/data/__init__.py
opsml/data/__init__.pyi
opsml/experiment/__init__.py
opsml/experiment/__init__.pyi
opsml/helpers/__init__.py
opsml/helpers/data.py
opsml/llm/__init__.py
opsml/llm/__init__.pyi
opsml/logging/__init__.py
opsml/logging/__init__.pyi
opsml/mock/__init__.py
opsml/mock/__init__.pyi
opsml/model/__init__.py
opsml/model/__init__.pyi
opsml/opsml.abi3.so
opsml/py.typed
opsml/scouter/__init__.py
opsml/scouter/__init__.pyi
opsml/scouter/alert/__init__.py
opsml/scouter/alert/__init__.pyi
opsml/scouter/client/__init__.py
opsml/scouter/client/__init__.pyi
opsml/scouter/drift/__init__.py
opsml/scouter/drift/__init__.pyi
opsml/scouter/observe/__init__.py
opsml/scouter/observe/__init__.pyi
opsml/scouter/profile/__init__.py
opsml/scouter/profile/__init__.pyi
opsml/scouter/queue/__init__.py
opsml/scouter/queue/__init__.pyi
opsml/scouter/types/__init__.py
opsml/scouter/types/__init__.pyi
opsml/scouter/util/__init__.py
opsml/types/__init__.py
opsml/types/__init__.pyi
opsml_client-3.0.0rc16.dist-info/METADATA
opsml_client-3.0.0rc16.dist-info/WHEEL
opsml_client-3.0.0rc16.dist-info/entry_points.txt
opsml_client-3.0.0rc16.dist-info/licenses/LICENSE
opsml_client-3.0.0rc16.dist-info/RECORD
