Metadata-Version: 2.4
Name: opsml-client
Version: 3.0.0rc16
Classifier: Programming Language :: Rust
Classifier: Programming Language :: Python :: Implementation :: CPython
Classifier: Programming Language :: Python :: Implementation :: PyPy
Requires-Dist: joblib~=1.3
Requires-Dist: pyarrow>=18.0.0
Requires-Dist: onnx>=1.16.0 ; python_full_version < '3.13' and platform_system == 'Linux' and extra == 'onnx'
Requires-Dist: onnx==1.16.1 ; platform_system == 'Windows' and extra == 'onnx'
Requires-Dist: onnx>=1.16.0 ; python_full_version < '3.13' and platform_system == 'Darwin' and extra == 'onnx'
Requires-Dist: onnx>=1.17.0 ; (python_full_version >= '3.12' and platform_system == 'Darwin' and extra == 'onnx') or (python_full_version >= '3.12' and platform_system == 'Linux' and extra == 'onnx')
Requires-Dist: onnxruntime>=1.18.0 ; extra == 'onnxruntime'
Requires-Dist: skl2onnx>=1.16.0,<1.20.0 ; extra == 'sklearn-onnx'
Requires-Dist: onnxmltools~=1.14 ; extra == 'sklearn-onnx'
Requires-Dist: opsml[onnx,onnxruntime] ; extra == 'sklearn-onnx'
Provides-Extra: onnx
Provides-Extra: onnxruntime
Provides-Extra: sklearn_onnx
License-File: LICENSE
Summary: 
Author-email: Thorrester <<support@demmlai.com>>
License-Expression: MIT
Requires-Python: >=3.10
